goutte/__init__.py
goutte/main.py
goutte-1.0.1.dist-info/entry_points.txt
goutte-1.0.1.dist-info/LICENSE
goutte-1.0.1.dist-info/WHEEL
goutte-1.0.1.dist-info/METADATA
goutte-1.0.1.dist-info/RECORD
